{
  "Projects": [
    {
      "name": "Casa Nova",
      "budget": "50000",
      "category": {
        "id": "1",
        "name": "Infra"
      },
      "cost": 0,
      "services": [],
      "id": 2
    },
    {
      "name": "Escola",
      "budget": "39999",
      "category": {
        "id": "4",
        "name": "Planejamento"
      },
      "cost": 0,
      "services": [],
      "id": 3
    },
    {
      "name": "Apartamento",
      "budget": "80053",
      "category": {
        "id": "2",
        "name": "Desenvolvimento"
      },
      "cost": 0,
      "services": [],
      "id": 4
    },
    {
      "name": "Piscina da casa de praia",
      "budget": "20008",
      "category": {
        "id": "3",
        "name": "Design"
      },
      "cost": 0,
      "services": [],
      "id": 6
    },
    {
      "name": "Viagem de fim de ano",
      "budget": "15000",
      "category": {
        "id": "4",
        "name": "Planejamento"
      },
      "cost": 0,
      "services": [],
      "id": 7
    },
    {
      "name": "Loja de informática",
      "budget": "35000",
      "category": {
        "id": "2",
        "name": "Desenvolvimento"
      },
      "cost": 0,
      "services": [],
      "id": 8
    }
  ],
  "Categories": [
    {
      "id": 1,
      "name": "Infra"
    },
    {
      "id": 2,
      "name": "Desenvolvimento"
    },
    {
      "id": 3,
      "name": "Design"
    },
    {
      "id": 4,
      "name": "Planejamento"
    }
  ]
}